protkit/__init__.py
protkit/core/__init__.py
protkit/core/extend_attributes.py
protkit/download/__init__.py
protkit/download/download.py
protkit/file_io/__init__.py
protkit/file_io/fasta_io.py
protkit/file_io/mmcif_io.py
protkit/file_io/mmtf_io.py
protkit/file_io/pdb_io.py
protkit/file_io/pqr_io.py
protkit/file_io/prot_io.py
protkit/geometry/__init__.py
protkit/geometry/math.py
protkit/geometry/space_query.py
protkit/metrics/__init__.py
protkit/metrics/classification_eval.py
protkit/metrics/regression_eval.py
protkit/metrics/scoring_matrix.py
protkit/metrics/sequence_eval.py
protkit/metrics/structure_eval.py
protkit/metrics/utility_eval.py
protkit/ml/__init__.py
protkit/ml/dataframe.py
protkit/properties/__init__.py
protkit/properties/bond_angles.py
protkit/properties/bond_lengths.py
protkit/properties/bounds.py
protkit/properties/charge.py
protkit/properties/chemical_class.py
protkit/properties/circular_variance.py
protkit/properties/dihedral_angles.py
protkit/properties/donors_acceptors.py
protkit/properties/hydrophobicity.py
protkit/properties/interface.py
protkit/properties/mass.py
protkit/properties/polarity.py
protkit/properties/surface_area.py
protkit/properties/vdw_radius.py
protkit/properties/volume.py
protkit/seq/__init__.py
protkit/seq/antibody_sequence.py
protkit/seq/nucleotide_sequence.py
protkit/seq/protein_sequence.py
protkit/seq/sequence.py
protkit/seq/sequence_alignment.py
protkit/structure/__init__.py
protkit/structure/atom.py
protkit/structure/chain.py
protkit/structure/protein.py
protkit/structure/residue.py
protkit/tasks/__init__.py
protkit/tasks/protonator.py
protkit/tasks/surface_area_calculator.py
protkit/tools/__init__.py
protkit/tools/abnumber_adaptor.py
protkit/tools/freesasa_adaptor.py
protkit/tools/pdb2pqr_adaptor.py
protkit/tools/propka_adaptor.py
protkit/tools/reduce_adaptor.py
tests/quick_start_guide.py
tests/test_biopandas.py
tests/test_featurizer.py
tests/test_occupancy_claudio.py
tests/test_pdb2pqr.py
tests/test_propka.py
protkit-0.3.0.dist-info/LICENSE
protkit-0.3.0.dist-info/METADATA
protkit-0.3.0.dist-info/WHEEL
protkit-0.3.0.dist-info/top_level.txt
protkit-0.3.0.dist-info/RECORD
