Metadata-Version: 2.1
Name: protkit
Version: 0.3.0
Summary: A unified toolkit for structural protein engineering.
Author-email: Fred Senekal <fred@silicogenesis.com>
Maintainer-email: Fred Senekal <fred@silicogenesis.com>
Project-URL: Homepage, https://protkit.silicogenesis.com
Project-URL: Repository, https://github.com/silicogenesis/protkit
Project-URL: Documentation, https://silicogenesis.github.io/protkit
Keywords: protein,protein engineering,structural biology,computational biology,biology,bioinformatics,sequence,amino acid,residue,dataset,PDB,antibody,antibody engineering,cdr
Classifier: Programming Language :: Python :: 3
Classifier: License :: OSI Approved :: GNU General Public License v3 (GPLv3)
Classifier: Operating System :: OS Independent
Requires-Python: >=3.6
License-File: LICENSE
Requires-Dist: requests>=2.31.0
Requires-Dist: joblib>=1.3.2
Requires-Dist: numpy>=1.20.3
Requires-Dist: scikit-learn>=1.4.1.post1
Requires-Dist: biopython>=1.83
Requires-Dist: mmtf-python>=1.1.3
Requires-Dist: freesasa>=2.2.1
Requires-Dist: pdb2pqr>=3.6.2
Requires-Dist: propka>=3.5.1
Requires-Dist: pandas>=2.2.2
Provides-Extra: dev
Requires-Dist: pytest>=6.2.5; extra == "dev"
Requires-Dist: setuptools>=61.0; extra == "dev"
